source_recurly/__init__.py
source_recurly/components.py
source_recurly/manifest.yaml
source_recurly/run.py
source_recurly/source.py
airbyte_source_recurly-1.1.13.dist-info/METADATA
airbyte_source_recurly-1.1.13.dist-info/WHEEL
airbyte_source_recurly-1.1.13.dist-info/entry_points.txt
airbyte_source_recurly-1.1.13.dist-info/RECORD
